{
  "Solv": {
    "start_timer": "", 
    "time_data": "", 
    "timer": "", 
    "coordinates": {
      "latitude": "",
      "longtude": ""
    }, 
    "height": "", 
    "svs": "", 
    "res": "", 
    "modi_ns": "", 
    "modi_ms": "", 
    "pdop": "", 
    "e_distance": "", 
    "appar_counter": ""
  },
  "Lct":{"number":[1,3,5,7],
    "time_data":[null,"06.05.2020",null,"06.05.2020",null,"06.05.2020",null,"06.05.2020"],
    "timer":[null,"11:33:24",null,"11:33:24",null,"11:33:24",null,"11:33:24"],
    "coordinates":{"latitude":[null,55.755407931,null,55.755565025,null,55.755609421,null,55.755769932],
      "longtude":[null,37.708320106,null,37.707794181,null,37.708576238,null,37.708057143]},
    "height":[null,163.416,null,163.629,null,163.564,null,163.473],
    "resids":[null,[null,0,-18,0,-128,-16,-128,-32,-128,-64,-128],
      null,[null,0,-128,-11,-128,17,-128,-54,-128,77,-128],null,
      [null,0,-128,-128,-128,-128,-128,-128,-128,-128,-128],null,
      [null,-128,-128,-64,-128,-32,-128,-16,-128,-64,-128]]}
}


// {
//   "Solv": {
//     "start_timer": "", //таймер приемника
//     "time_data": "", //дата число.месяц.год
//     "timer": "", //местное время
//     "coordinates": {
//       "latitude": "",
//       "longtude": ""
//     }, //координаты широта долгоа
//     "height": "", //высота
//     "svs": "", //сколько маяков было задействавоно для решения нав.задачи
//     "res": "", //среднеквадратическая невязка решения навигационной задачи (насколько бьются измерения между собой)
//     "modi_ns": "", //поправка к шкале времени
//     "modi_ms": "", //поправка к шкале скорости
//     "pdop": "", //геометрический фактор
//     "e_distance": "", //расстояние до базы
//     "appar_counter": "" //аппаратный счетчик
//   },
//   "Lct": {
//     "number": "", //номера существующих маяков
//     "time_data": "", //дата число.месяц.год
//     "timer": "", //местное время
//     "coordinates": {
//       "latitude": "",
//       "longtude": ""
//     }, //координаты широта долгоа
//     "height": "", //высота
//     "resids": "" //невязки
//   }
// }

// {"Solv":{"start_timer":301.00008200000002,"time_data":"2020/05/06",
//   "timer":"11:33:41.200250375","coordinates":{"latitude":"55.75546",
//     "longtude":"37.708032"},"height":162.947,"svs":"4/4","res":0.08,
//   "modi_ns":"+0.0+-5e+02","modi_ms":"r2s=+38.2+-0.3","pdop":1.8009087530980,"e_distance":313,
//   "appar_counter":455.035},
  // "Lct":{"number":[1,3,5,7],
  //   "time_data":[null,"06.05.2020",null,"06.05.2020",null,"06.05.2020",null,"06.05.2020"],
  //   "timer":[null,"11:33:24",null,"11:33:24",null,"11:33:24",null,"11:33:24"],
  //   "coordinates":{"latitude":[null,55.755407931,null,55.755565025,null,55.755609421,null,55.755769932],
  //     "longtude":[null,37.708320106,null,37.707794181,null,37.708576238,null,37.708057143]},
  //   "height":[null,163.416,null,163.629,null,163.564,null,163.473],
  //   "resids":[null,[null,0,-18,0,-128,-16,-128,-32,-128,-64,-128],
  //     null,[null,0,-128,-11,-128,17,-128,-54,-128,77,-128],null,
  //     [null,0,-128,-128,-128,-128,-128,-128,-128,-128,-128],null,
  //     [null,-128,-128,-64,-128,-32,-128,-16,-128,-64,-128]]}}

